lfarazgoated/__init__.py
lfarazgoated/py.typed
lfarazgoated/_jsii/__init__.py
lfarazgoated/_jsii/farazgoated@0.0.4.jsii.tgz
farazgoated-0.0.4.dist-info/LICENSE
farazgoated-0.0.4.dist-info/METADATA
farazgoated-0.0.4.dist-info/WHEEL
farazgoated-0.0.4.dist-info/top_level.txt
farazgoated-0.0.4.dist-info/RECORD
